sk_serve/__init__.py
sk_serve/api.py
sk_serve/serve.py
simple_serve-1.1.0.dist-info/METADATA
simple_serve-1.1.0.dist-info/WHEEL
simple_serve-1.1.0.dist-info/licenses/LICENSE
simple_serve-1.1.0.dist-info/RECORD
