Metadata-Version: 2.4
Name: simple_serve
Version: 1.1.0
Summary: Deployment of a Scikit-Learn model and it's column transformations with a single endpoint.
Project-URL: Homepage, https://github.com/alexliap/sk_serve
Project-URL: Documentation, https://alexliap.github.io/sk_serve/
Project-URL: Repository, https://github.com/alexliap/sk_serve
Project-URL: Issues, https://github.com/alexliap/sk_serve/issues
Author-email: Alexandros Liapatis <alexandrosliapatis@gmail.com>
Maintainer-email: Alexandros Liapatis <alexandrosliapatis@gmail.com>
License: MIT License
License-File: LICENSE
Requires-Python: >=3.12
Requires-Dist: fastapi
Requires-Dist: loguru
Requires-Dist: pandas
Requires-Dist: pydantic
Requires-Dist: scikit-learn
Requires-Dist: uvicorn>=0.35.0
Provides-Extra: dev
Requires-Dist: pre-commit; extra == 'dev'
Requires-Dist: pyright; extra == 'dev'
